odoo8_addon_mobile_app_inventory-8.0.2.0.0.99.dev3-py2.7-nspkg.pth
odoo8_addon_mobile_app_inventory-8.0.2.0.0.99.dev3.dist-info/METADATA
odoo8_addon_mobile_app_inventory-8.0.2.0.0.99.dev3.dist-info/RECORD
odoo8_addon_mobile_app_inventory-8.0.2.0.0.99.dev3.dist-info/WHEEL
odoo8_addon_mobile_app_inventory-8.0.2.0.0.99.dev3.dist-info/namespace_packages.txt
odoo8_addon_mobile_app_inventory-8.0.2.0.0.99.dev3.dist-info/top_level.txt
odoo_addons/mobile_app_inventory/README.rst
odoo_addons/mobile_app_inventory/__init__.py
odoo_addons/mobile_app_inventory/__openerp__.py
odoo_addons/mobile_app_inventory/post_install.py
odoo_addons/mobile_app_inventory/demo/product_product.xml
odoo_addons/mobile_app_inventory/demo/res_company.xml
odoo_addons/mobile_app_inventory/demo/res_users.xml
odoo_addons/mobile_app_inventory/demo/stock_inventory.xml
odoo_addons/mobile_app_inventory/demo/stock_location.xml
odoo_addons/mobile_app_inventory/i18n/am.po
odoo_addons/mobile_app_inventory/i18n/ar.po
odoo_addons/mobile_app_inventory/i18n/ca.po
odoo_addons/mobile_app_inventory/i18n/da.po
odoo_addons/mobile_app_inventory/i18n/de.po
odoo_addons/mobile_app_inventory/i18n/el_GR.po
odoo_addons/mobile_app_inventory/i18n/es.po
odoo_addons/mobile_app_inventory/i18n/es_ES.po
odoo_addons/mobile_app_inventory/i18n/es_MX.po
odoo_addons/mobile_app_inventory/i18n/fi.po
odoo_addons/mobile_app_inventory/i18n/fr.po
odoo_addons/mobile_app_inventory/i18n/fr_CA.po
odoo_addons/mobile_app_inventory/i18n/fr_CH.po
odoo_addons/mobile_app_inventory/i18n/fr_FR.po
odoo_addons/mobile_app_inventory/i18n/gl.po
odoo_addons/mobile_app_inventory/i18n/hr.po
odoo_addons/mobile_app_inventory/i18n/hr_HR.po
odoo_addons/mobile_app_inventory/i18n/it.po
odoo_addons/mobile_app_inventory/i18n/mobile_app_inventory.pot
odoo_addons/mobile_app_inventory/i18n/nb.po
odoo_addons/mobile_app_inventory/i18n/nb_NO.po
odoo_addons/mobile_app_inventory/i18n/nl.po
odoo_addons/mobile_app_inventory/i18n/nl_BE.po
odoo_addons/mobile_app_inventory/i18n/nl_NL.po
odoo_addons/mobile_app_inventory/i18n/pt.po
odoo_addons/mobile_app_inventory/i18n/pt_BR.po
odoo_addons/mobile_app_inventory/i18n/pt_PT.po
odoo_addons/mobile_app_inventory/i18n/ro.po
odoo_addons/mobile_app_inventory/i18n/ru.po
odoo_addons/mobile_app_inventory/i18n/sk.po
odoo_addons/mobile_app_inventory/i18n/sl.po
